Facebook_Chat_Analysis/Facebook_Chat_Analysis.py
Facebook_Chat_Analysis/__init__.py
Facebook_Chat_Analysis-0.3.dist-info/LICENSE
Facebook_Chat_Analysis-0.3.dist-info/METADATA
Facebook_Chat_Analysis-0.3.dist-info/WHEEL
Facebook_Chat_Analysis-0.3.dist-info/top_level.txt
Facebook_Chat_Analysis-0.3.dist-info/RECORD
