Metadata-Version: 2.1
Name: Facebook_Chat_Analysis
Version: 0.3
Summary: Pre-Process and Analyse Facebook Messenger Chats
Home-page: https://github.com/mario-likes-camels/Facebook_Chat_Analysis
Author: Patrick
Author-email: hi_in@hotmail.com
License: MIT
Platform: UNKNOWN
License-File: LICENSE
